equinor_libres-11.0.1.data/data/share/ert/site-config
equinor_libres-11.0.1.data/data/share/ert/forward-models/docs/description/CAREFUL_COPY_FILE.rst
equinor_libres-11.0.1.data/data/share/ert/forward-models/docs/description/COPY_DIRECTORY.rst
equinor_libres-11.0.1.data/data/share/ert/forward-models/docs/description/COPY_FILE.rst
equinor_libres-11.0.1.data/data/share/ert/forward-models/docs/description/DELETE_DIRECTORY.rst
equinor_libres-11.0.1.data/data/share/ert/forward-models/docs/description/DELETE_FILE.rst
equinor_libres-11.0.1.data/data/share/ert/forward-models/docs/description/MAKE_DIRECTORY.rst
equinor_libres-11.0.1.data/data/share/ert/forward-models/docs/description/MAKE_SYMLINK.rst
equinor_libres-11.0.1.data/data/share/ert/forward-models/docs/description/MOVE_FILE.rst
equinor_libres-11.0.1.data/data/share/ert/forward-models/docs/description/RMS.rst
equinor_libres-11.0.1.data/data/share/ert/forward-models/docs/description/SYMLINK.rst
equinor_libres-11.0.1.data/data/share/ert/forward-models/docs/description/TEMPLATE_RENDER.rst
equinor_libres-11.0.1.data/data/share/ert/forward-models/docs/examples/CAREFUL_COPY_FILE.rst
equinor_libres-11.0.1.data/data/share/ert/forward-models/docs/examples/COPY_FILE.rst
equinor_libres-11.0.1.data/data/share/ert/forward-models/docs/examples/ECLIPSE100.rst
equinor_libres-11.0.1.data/data/share/ert/forward-models/docs/examples/ECLIPSE300.rst
equinor_libres-11.0.1.data/data/share/ert/forward-models/docs/examples/FLOW.rst
equinor_libres-11.0.1.data/data/share/ert/forward-models/docs/examples/RMS.rst
equinor_libres-11.0.1.data/data/share/ert/forward-models/docs/examples/TEMPLATE_RENDER.rst
equinor_libres-11.0.1.data/data/share/ert/forward-models/old_style/CAREFUL_COPY_FILE
equinor_libres-11.0.1.data/data/share/ert/forward-models/old_style/COPY_DIRECTORY
equinor_libres-11.0.1.data/data/share/ert/forward-models/old_style/COPY_FILE
equinor_libres-11.0.1.data/data/share/ert/forward-models/old_style/DELETE_DIRECTORY
equinor_libres-11.0.1.dist-info/COPYING
equinor_libres-11.0.1.dist-info/METADATA
equinor_libres-11.0.1.dist-info/WHEEL
equinor_libres-11.0.1.dist-info/entry_points.txt
equinor_libres-11.0.1.dist-info/top_level.txt
equinor_libres-11.0.1.dist-info/RECORD
