Metadata-Version: 2.1
Name: equinor-libres
Version: 11.0.1
Summary: Part of the Ensemble based Reservoir Tool (ERT)
Home-page: https://github.com/equinor/libres
Author: Equinor ASA
Author-email: fg_sib-scout@equinor.com
License: GPL-3.0
Platform: any
Classifier: Development Status :: 5 - Production/Stable
Classifier: Environment :: Other Environment
Classifier: Intended Audience :: Developers
Classifier: Intended Audience :: Science/Research
Classifier: License :: OSI Approved :: GNU General Public License v3 (GPLv3)
Classifier: Natural Language :: English
Classifier: Programming Language :: Python
Classifier: Programming Language :: Python :: 3.6
Classifier: Programming Language :: Python :: 3.7
Classifier: Programming Language :: Python :: 3.8
Classifier: Programming Language :: Python :: 3.9
Classifier: Topic :: Scientific/Engineering
Classifier: Topic :: Scientific/Engineering :: Physics
Classifier: Topic :: Software Development :: Libraries
Classifier: Topic :: Utilities
License-File: COPYING
Requires-Dist: cloudevents
Requires-Dist: cwrap
Requires-Dist: ecl
Requires-Dist: jinja2
Requires-Dist: numpy
Requires-Dist: pandas
Requires-Dist: psutil
Requires-Dist: pyyaml
Requires-Dist: requests
Requires-Dist: websockets (>=9.0.1)
